crc32c/__init__.py
crc32c/_cli.py
crc32c/_crc32c.cpython-310-x86_64-linux-gnu.so
crc32c/_crc32c.pyi
crc32c/_crc32hash.py
crc32c/benchmark.py
crc32c/py.typed
crc32c/ext/_crc32c.c
crc32c/ext/checkarm.c
crc32c/ext/checkarm.h
crc32c/ext/checksse42.c
crc32c/ext/checksse42.h
crc32c/ext/common.h
crc32c/ext/crc32c.h
crc32c/ext/crc32c_adler.c
crc32c/ext/crc32c_arm64.c
crc32c/ext/crc32c_sw.c
crc32c-2.8.dist-info/METADATA
crc32c-2.8.dist-info/WHEEL
crc32c-2.8.dist-info/entry_points.txt
crc32c-2.8.dist-info/top_level.txt
crc32c-2.8.dist-info/RECORD
crc32c-2.8.dist-info/licenses/AUTHORS.google-crc32c
crc32c-2.8.dist-info/licenses/LICENSE
crc32c-2.8.dist-info/licenses/LICENSE.google-crc32c
crc32c-2.8.dist-info/licenses/LICENSE.slice-by-8
