Metadata-Version: 2.1
Name: crc32c
Version: 2.8
Summary: A python package implementing the crc32c algorithm in hardware and software
Author-email: Rodrigo Tobar <rtobar@icrar.org>
License: LGPL-2.1-or-later
Project-URL: github, https://github.com/ICRAR/crc32c
Project-URL: changelog, https://github.com/ICRAR/crc32c/blob/master/CHANGELOG.md
Project-URL: issues, https://github.com/ICRAR/crc32c/issues
Classifier: License :: OSI Approved :: GNU Lesser General Public License v2 or later (LGPLv2+)
Classifier: Operating System :: OS Independent
Classifier: Programming Language :: C
Classifier: Programming Language :: Python :: 3.7
Classifier: Programming Language :: Python :: 3.8
Classifier: Programming Language :: Python :: 3.9
Classifier: Programming Language :: Python :: 3.10
Classifier: Programming Language :: Python :: 3.11
Classifier: Programming Language :: Python :: 3.12
Classifier: Programming Language :: Python :: 3.13
Classifier: Programming Language :: Python :: 3.14
Requires-Python: >=3.7
License-File: LICENSE
License-File: LICENSE.google-crc32c
License-File: LICENSE.slice-by-8
License-File: AUTHORS.google-crc32c
